blissful_basics/__init__.py
blissful_basics/settings.json
blissful_basics/update_dependencies
blissful_basics/__dependencies__/__init__.py
blissful_basics/__dependencies__/__sources__/file_system_py/.gitignore
blissful_basics/__dependencies__/__sources__/file_system_py/.gitrepo
blissful_basics/__dependencies__/__sources__/file_system_py/README.md
blissful_basics/__dependencies__/__sources__/file_system_py/poetry.lock
blissful_basics/__dependencies__/__sources__/file_system_py/pyproject.toml
blissful_basics/__dependencies__/__sources__/file_system_py/commands/pip
blissful_basics/__dependencies__/__sources__/file_system_py/commands/shell
blissful_basics/__dependencies__/__sources__/file_system_py/commands/start
blissful_basics/__dependencies__/__sources__/file_system_py/commands/subrepo
blissful_basics/__dependencies__/__sources__/file_system_py/commands/project/clean
blissful_basics/__dependencies__/__sources__/file_system_py/commands/project/commands
blissful_basics/__dependencies__/__sources__/file_system_py/commands/project/local_install
blissful_basics/__dependencies__/__sources__/file_system_py/commands/project/publish
blissful_basics/__dependencies__/__sources__/file_system_py/commands/project/purge
blissful_basics/__dependencies__/__sources__/file_system_py/documentation/fornix_framework.md
blissful_basics/__dependencies__/__sources__/file_system_py/documentation/setup.md
blissful_basics/__dependencies__/__sources__/file_system_py/documentation/images/cd_tutorial.gif
blissful_basics/__dependencies__/__sources__/file_system_py/documentation/images/package_from_example.png
blissful_basics/__dependencies__/__sources__/file_system_py/documentation/images/package_name.png
blissful_basics/__dependencies__/__sources__/file_system_py/documentation/images/package_versions.png
blissful_basics/__dependencies__/__sources__/file_system_py/logs/main.py.log
blissful_basics/__dependencies__/__sources__/file_system_py/main/.keep
blissful_basics-0.2.37.dist-info/METADATA
blissful_basics-0.2.37.dist-info/WHEEL
blissful_basics-0.2.37.dist-info/top_level.txt
blissful_basics-0.2.37.dist-info/RECORD
