Metadata-Version: 2.1
Name: blissful-basics
Version: 0.2.37
Summary: Tools I need in every python project
Home-page: https://github.com/jeff-hykin/blissful_basics.git
Author: Jeff Hykin
Author-email: jeff.hykin@gmail.com
License: MIT
Platform: UNKNOWN
Requires-Python: >=3.6
